{"_path":"/works/brainwash","_dir":"works","_draft":false,"_partial":false,"_locale":"","_empty":false,"title":"Brainwash / Gehirnwäsche","description":"Modified washing machine","type":"art project","year":2011,"tags":["art","hacking","video","installation","mobile app"],"img":"imgs/brainwash-1.jpg","body":{"type":"root","children":[{"type":"element","tag":"p","props":{},"children":[{"type":"text","value":"Closed-circuit video installation, built from a deranged washing machine with a\nlittle help from a video camera, a Raspberry Pi, and a screen."}]},{"type":"element","tag":"div","props":{"className":["videoWrapper"]},"children":[{"type":"text","value":"\n  "},{"type":"element","tag":"iframe","props":{"src":"https://player.vimeo.com/video/204761873","width":640,"height":360,"frameBorder":"0","allow":"autoplay; fullscreen","allowFullScreen":true},"children":[{"type":"text","value":"\n  "}]}]},{"type":"element","tag":"div","props":{"className":["videoWrapper"]},"children":[{"type":"text","value":"\n  "},{"type":"element","tag":"iframe","props":{"width":560,"height":315,"src":"https://www.youtube.com/embed/1KG0YLNkUZc","frameBorder":"0","allow":"accelerometer; autoplay; encrypted-media; gyroscope; picture-in-picture","allowFullScreen":true},"children":[{"type":"text","value":"\n  "}]}]},{"type":"element","tag":"style","props":{"type":"text/css"},"children":[{"type":"text","value":"\n.videoWrapper {\n  position: relative;\n  padding-bottom: 56.25%; /* 16:9 */\n  height: 0;\n  margin-top: 20px;\n  margin-bottom: 20px;\n}\n.videoWrapper iframe {\n  position: absolute;\n  top: 0;\n  left: 0;\n  width: 100%;\n  height: 100%;\n}\n"}]},{"type":"element","tag":"p","props":{},"children":[{"type":"text","value":"collaborators:"}]},{"type":"element","tag":"ul","props":{},"children":[{"type":"element","tag":"li","props":{},"children":[{"type":"element","tag":"a","props":{"href":"https://www.anneglassner.at","rel":["nofollow"]},"children":[{"type":"text","value":"Anne Glassner"}]}]},{"type":"element","tag":"li","props":{},"children":[{"type":"text","value":"Stefan Pomajbik"}]},{"type":"element","tag":"li","props":{},"children":[{"type":"text","value":"Dirk Budig"}]}]}],"toc":{"title":"","searchDepth":2,"depth":2,"links":[]}},"_type":"markdown","_id":"content:works:brainwash.md","_source":"content","_file":"works/brainwash.md","_extension":"md"}